xpore/__init__.py
xpore/diffmod/__init__.py
xpore/diffmod/configurator.py
xpore/diffmod/gmm.py
xpore/diffmod/io.py
xpore/diffmod/model_kmer.csv
xpore/diffmod/statstest.py
xpore/scripts/__init__.py
xpore/scripts/backdoor.py
xpore/scripts/dataprep.py
xpore/scripts/diffmod.py
xpore/scripts/helper.py
xpore/scripts/postprocessing.py
xpore/scripts/xpore.py
xpore/utils/__init__.py
xpore/utils/misc.py
xpore/utils/stats.py
xpore-2.1.dist-info/LICENSE
xpore-2.1.dist-info/METADATA
xpore-2.1.dist-info/WHEEL
xpore-2.1.dist-info/entry_points.txt
xpore-2.1.dist-info/top_level.txt
xpore-2.1.dist-info/RECORD
