Metadata-Version: 2.1
Name: xpore
Version: 2.1
Summary: xpore is a python package for Nanopore data analysis of differential RNA modifications.
Home-page: https://github.com/GoekeLab/xpore
Author: Ploy N. Pratanwanich
Maintainer-email: naruemon.p@chula.ac.th
License: MIT
Platform: UNKNOWN
Classifier: Development Status :: 1 - Planning
Classifier: License :: OSI Approved :: MIT License
Classifier: Programming Language :: Python
Classifier: Programming Language :: Python :: 3.8
Classifier: Topic :: Software Development :: Libraries
Classifier: Topic :: Scientific/Engineering :: Bio-Informatics
Classifier: Intended Audience :: Science/Research
Requires-Python: >=3.8
Requires-Dist: numpy (>=1.18.0)
Requires-Dist: pandas (>=0.25.3)
Requires-Dist: scipy (>=1.4.1)
Requires-Dist: PyYAML
Requires-Dist: h5py (>=2.10.0)
Requires-Dist: pyensembl (>=1.8.5)
Requires-Dist: ujson (>=4.0.1)
